odoo/addons/ssi_transaction_total_mixin/README.rst
odoo/addons/ssi_transaction_total_mixin/__init__.py
odoo/addons/ssi_transaction_total_mixin/__manifest__.py
odoo/addons/ssi_transaction_total_mixin/models/__init__.py
odoo/addons/ssi_transaction_total_mixin/models/mixin_transaction_residual.py
odoo/addons/ssi_transaction_total_mixin/models/mixin_transaction_tax.py
odoo/addons/ssi_transaction_total_mixin/models/mixin_transaction_total.py
odoo/addons/ssi_transaction_total_mixin/models/mixin_transaction_untaxed.py
odoo/addons/ssi_transaction_total_mixin/static/description/icon.png
odoo14_addon_ssi_transaction_total_mixin-14.0.1.0.1.dist-info/METADATA
odoo14_addon_ssi_transaction_total_mixin-14.0.1.0.1.dist-info/WHEEL
odoo14_addon_ssi_transaction_total_mixin-14.0.1.0.1.dist-info/top_level.txt
odoo14_addon_ssi_transaction_total_mixin-14.0.1.0.1.dist-info/RECORD
